aioli_openapi/__init__.py
aioli_openapi/config.py
aioli_openapi/controller.py
aioli_openapi/schema.py
aioli_openapi/service.py
aioli_openapi-0.2.0.dist-info/LICENSE
aioli_openapi-0.2.0.dist-info/WHEEL
aioli_openapi-0.2.0.dist-info/METADATA
aioli_openapi-0.2.0.dist-info/RECORD
