Metadata-Version: 2.1
Name: aioli-openapi
Version: 0.2.0
Summary: Generate OpenAPI schemas using Aioli Handlers
Home-page: https://github.com/aioli-framework/aioli-openapi
License: MIT
Keywords: aioli_package
Author: Robert Wikman
Author-email: rbw@vault13.org
Requires-Python: >=3.6,<4.0
Classifier: License :: OSI Approved :: MIT License
Classifier: Programming Language :: Python :: 3
Classifier: Programming Language :: Python :: 3.6
Classifier: Programming Language :: Python :: 3.7
Requires-Dist: aioli (>=0.5.0,<0.6.0)
Requires-Dist: apispec (>=2.0.1,<3.0.0)
